{
    "Description": "<<changelog>>",
    "OSversion": "Amazon Linux 2",
    "ShortVersion": "AMZN2",
    "AccountId": "",
    "AMIDetails": {
        "us-east-1": "<<AMI-ID1>>",
        "us-west-2": "<<AMI-ID2>>",
        "eu-west-1": "<<AMI-ID3>>",
        "eu-central-1": "<<AMI-ID4>>",
        "ap-southeast-1": "<<AMI-ID5>>",
        "ap-northeast-1": "<<AMI-ID6>>"
    },
    "Metadata": {
        "Comments": "Metadata section is used to assign Name tags to AMIs",
        "MajorReleaseVersion": "v1",
        "PurposeCode": "GOLDEN",
        "Osname": "LIN",
        "Osversion": "2",
        "Regions": {
            "us-east-1": {
                "Country": "US",
                "Location": "VGA"
            },
            "us-west-2": {
                "Country": "US",
                "Location": "ORE"
            },
            "eu-west-1": {
                "Country": "IE",
                "Location": "MUL"
            },
            "eu-central-1": {
                "Country": "DE",
                "Location": "FRA"
            },
            "ap-southeast-1": {
                "Country": "SG",
                "Location": "SGP"
            },
            "ap-northeast-1": {
                "Country": "JP",
                "Location": "TKO"
            }
        }
    }
}